networkdisk/__init__.py
networkdisk/exception.py
networkdisk/py.typed
networkdisk/mock/__init__.py
networkdisk/mock/copymock.py
networkdisk/mock/nxmock.py
networkdisk/oracle/columns
networkdisk/oracle/dialect.py
networkdisk/oracle/digraph
networkdisk/oracle/graph
networkdisk/oracle/helper
networkdisk/oracle/queries.py
networkdisk/oracle/schema
networkdisk/oracle/tupledict
networkdisk/sql/__init__.py
networkdisk/sql/columns.py
networkdisk/sql/conditions.py
networkdisk/sql/constants.py
networkdisk/sql/constraints.py
networkdisk/sql/dialect.py
networkdisk/sql/digraph.py
networkdisk/sql/function.py
networkdisk/sql/graph.py
networkdisk/sql/graph_schema.py
networkdisk/sql/helper.py
networkdisk/sql/master.py
networkdisk/sql/queries.py
networkdisk/sql/schema.py
networkdisk/sql/scope.py
networkdisk/sql/sqllogging.py
networkdisk/sql/transaction.py
networkdisk/sql/tupledict.py
networkdisk/sql/classes/__init__.py
networkdisk/sql/classes/coreviews.py
networkdisk/sql/classes/graphviews.py
networkdisk/sql/classes/reportviews.py
networkdisk/sql/schemata/__init__.py
networkdisk/sql/schemata/digraph.py
networkdisk/sql/schemata/ungraph.py
networkdisk/sql/tests/__init__.py
networkdisk/sql/tests/test_condition.py
networkdisk/sql/tests/test_queries.py
networkdisk/sql/tests/test_schema.py
networkdisk/sql/tests/test_tupledict.py
networkdisk/sqlite/__init__.py
networkdisk/sqlite/columns.py
networkdisk/sqlite/dialect.py
networkdisk/sqlite/digraph.py
networkdisk/sqlite/graph.py
networkdisk/sqlite/graph_schema.py
networkdisk/sqlite/helper.py
networkdisk/sqlite/master.py
networkdisk/sqlite/queries.py
networkdisk/sqlite/schema.py
networkdisk/sqlite/tupledict.py
networkdisk/sqlite/tests/__init__.py
networkdisk/sqlite/tests/test_queries.py
networkdisk/sqlite/tests/test_schema.py
networkdisk/sqlite/tests/test_tupledict.py
networkdisk/testing/README
networkdisk/testing/__init__.py
networkdisk/testing/test.py
networkdisk/tests/__init__.py
networkdisk/tests/divergence.py
networkdisk/tests/nx_scrap.py
networkdisk-1.1.9.dist-info/METADATA
networkdisk-1.1.9.dist-info/WHEEL
networkdisk-1.1.9.dist-info/licenses/LICENSE.txt
networkdisk-1.1.9.dist-info/RECORD
