Metadata-Version: 2.3
Name: networkdisk
Version: 1.1.9
Summary: NetworkDisk: On disk graph manipulation
Project-URL: Homepage, https://networkdisk.inria.fr
Project-URL: documentation, https://networkdisk.inria.fr/documentation
Project-URL: repository, https://gitlab.inria.fr/guillonb/networkdisk
Author-email: Bruno Guillon <bruno.guillon@uca.fr>, Charles Paperman <charles.paperman@univ-lille.fr>
License: BSD-3-Clause
Keywords: database,graph,networkx
Classifier: Development Status :: 4 - Beta
Classifier: License :: OSI Approved :: BSD License
Classifier: Topic :: Utilities
Requires-Dist: networkx<=2.8,>=2.5
Requires-Dist: termcolor
Provides-Extra: all
Requires-Dist: matplotlib; extra == 'all'
Requires-Dist: more-itertools; extra == 'all'
Requires-Dist: mypy; extra == 'all'
Requires-Dist: numpydoc; extra == 'all'
Requires-Dist: pytest; extra == 'all'
Requires-Dist: pytest-cov; extra == 'all'
Requires-Dist: ruff; extra == 'all'
Requires-Dist: sphinx; extra == 'all'
Requires-Dist: sphinx-autorun; extra == 'all'
Requires-Dist: sphinx-copybutton; extra == 'all'
Requires-Dist: sphinx-rtd-theme; extra == 'all'
Provides-Extra: dev
Requires-Dist: mypy; extra == 'dev'
Requires-Dist: ruff; extra == 'dev'
Provides-Extra: doc
Requires-Dist: matplotlib; extra == 'doc'
Requires-Dist: numpydoc; extra == 'doc'
Requires-Dist: sphinx; extra == 'doc'
Requires-Dist: sphinx-autorun; extra == 'doc'
Requires-Dist: sphinx-copybutton; extra == 'doc'
Requires-Dist: sphinx-rtd-theme; extra == 'doc'
Provides-Extra: test
Requires-Dist: matplotlib; extra == 'test'
Requires-Dist: more-itertools; extra == 'test'
Requires-Dist: numpydoc; extra == 'test'
Requires-Dist: pytest; extra == 'test'
Requires-Dist: pytest-cov; extra == 'test'
Requires-Dist: sphinx; extra == 'test'
Requires-Dist: sphinx-autorun; extra == 'test'
Requires-Dist: sphinx-copybutton; extra == 'test'
Requires-Dist: sphinx-rtd-theme; extra == 'test'
